lacuscore/__init__.py
lacuscore/helpers.py
lacuscore/lacus_monitoring.py
lacuscore/lacuscore.py
lacuscore/py.typed
lacuscore/task_logger.py
lacuscore-1.21.1.dist-info/METADATA
lacuscore-1.21.1.dist-info/WHEEL
lacuscore-1.21.1.dist-info/licenses/LICENSE
lacuscore-1.21.1.dist-info/RECORD
