Metadata-Version: 2.4
Name: lacuscore
Version: 1.21.1
Summary: Core of Lacus, usable as a module
License-Expression: BSD-3-Clause
License-File: LICENSE
Author: Raphaël Vinot
Author-email: raphael.vinot@circl.lu
Requires-Python: >=3.10,<4.0
Classifier: Development Status :: 5 - Production/Stable
Classifier: Environment :: Console
Classifier: Intended Audience :: Information Technology
Classifier: Intended Audience :: Science/Research
Classifier: Intended Audience :: Telecommunications Industry
Classifier: Operating System :: POSIX :: Linux
Classifier: Programming Language :: Python :: 3
Classifier: Programming Language :: Python :: 3.10
Classifier: Programming Language :: Python :: 3.11
Classifier: Programming Language :: Python :: 3.12
Classifier: Programming Language :: Python :: 3.13
Classifier: Programming Language :: Python :: 3.14
Classifier: Topic :: Internet
Classifier: Topic :: Security
Provides-Extra: docs
Requires-Dist: Sphinx (>=9.1.0) ; (python_version >= "3.12") and (extra == "docs")
Requires-Dist: async-timeout (>=5.0.1) ; python_version < "3.11"
Requires-Dist: defang (>=0.5.3)
Requires-Dist: dnspython (>=2.8.0)
Requires-Dist: orjson (>=3.11.3,<4.0.0)
Requires-Dist: playwrightcapture[recaptcha] (>=1.36.1)
Requires-Dist: pydantic (>=2.12.5)
Requires-Dist: redis[hiredis] (>=5.3.0,<6.0.0)
Requires-Dist: requests (>=2.32.5)
Requires-Dist: typing-extensions (>=4.12.2,<5.0.0) ; python_version < "3.12"
Requires-Dist: ua-parser[regex] (>=1.0.1)
Project-URL: Documentation, https://lacuscore.readthedocs.io/en/latest/
Project-URL: Issues, https://github.com/ail-project/issues
Project-URL: Repository, https://github.com/ail-project/LacusCore
